dora_outtetts/__init__.py
dora_outtetts/__main__.py
dora_outtetts/main.py
dora_outtetts/tests/test_main.py
dora_outtetts-0.4.1.dist-info/METADATA
dora_outtetts-0.4.1.dist-info/WHEEL
dora_outtetts-0.4.1.dist-info/entry_points.txt
dora_outtetts-0.4.1.dist-info/top_level.txt
dora_outtetts-0.4.1.dist-info/RECORD
