Metadata-Version: 2.4
Name: dora-outtetts
Version: 0.4.1
Summary: dora-outtetts
License: MIT
Requires-Python: >=3.10
Requires-Dist: dora-rs>=0.3.9
Requires-Dist: numpy<2.0.0
Requires-Dist: pyarrow>=5.0.0
Requires-Dist: outetts>=0.2.3
Requires-Dist: llama-cpp-python>=0.2.0
